bifrost/__init__.py
bifrost/client.py
bifrost/storage.py
bifrost_ai-1.0.0.dist-info/METADATA
bifrost_ai-1.0.0.dist-info/WHEEL
bifrost_ai-1.0.0.dist-info/top_level.txt
bifrost_ai-1.0.0.dist-info/RECORD
